[
  {
    "id": "1784453334091-779",
    "table": 1,
    "items": [
      {
        "id": "set1",
        "name": "หมูกระทะเซ็ต (2 ท่าน)",
        "unit": "ชุด",
        "price": 199,
        "qty": 1
      },
      {
        "id": "veg",
        "name": "ผักรวม (จานเพิ่ม)",
        "unit": "จาน",
        "price": 49,
        "qty": 1
      }
    ],
    "total": 248,
    "status": "served",
    "paid": true,
    "createdAt": "2026-07-19T09:28:54.091Z"
  },
  {
    "id": "1784453342375-881",
    "table": 1,
    "items": [
      {
        "id": "water",
        "name": "น้ำเปล่า",
        "unit": "ขวด",
        "price": 15,
        "qty": 1
      },
      {
        "id": "ice",
        "name": "น้ำแข็ง",
        "unit": "ถุง",
        "price": 10,
        "qty": 1
      }
    ],
    "total": 25,
    "status": "served",
    "paid": true,
    "createdAt": "2026-07-19T09:29:02.375Z"
  }
]